modules/pe/pe.sv
// Final goal is to make a weight-stationary systolic array

module pe #(
// Subject to change
    parameter ACT_WIDTH = 16,
    parameter WT_WIDTH = 16,
    parameter PSUM_WIDTH = 32                       // to prevent overflow.
)(
    input  logic clk,
    input  logic rst_n,
    input  logic en,                                // 1: activates the PE,     0: freezes it
    input  logic load_weight,                       // 1: loads in new weight,  0: latches current weight, compute MAC. 

    // Data Inputs
    input  logic signed [ACT_WIDTH-1:0]  act_in,    // From left PE (or Skew FIFO)
    input  logic signed [WT_WIDTH-1:0]   weight_in, // From top PE (or Weight FIFO)
    input  logic signed [PSUM_WIDTH-1:0] psum_in,   // From top PE (or set to 0 at top row)

    // Data Outputs
    output logic signed [ACT_WIDTH-1:0]  act_out,   // To right PE
    output logic signed [PSUM_WIDTH-1:0] psum_out   // To bottom PE (or ReLU block)
);

    // Internal registers
    logic signed [WT_WIDTH-1:0] weight_reg;
    logic signed [ACT_WIDTH-1:0]  act_reg;
    logic signed [PSUM_WIDTH-1:0] psum_reg;

    assign act_out = act_reg;
    assign psum_out = psum_reg;

    logic signed [ACT_WIDTH+WT_WIDTH-1:0] prod;
    assign prod = act_in * weight_reg;

    always_ff @(posedge clk or negedge rst_n) begin
        if (!rst_n) begin
            weight_reg <= '0;
            act_reg    <= '0;
            psum_reg   <= '0;
        end else begin
            if (load_weight) begin
                weight_reg <= weight_in;
            end
            else if (en) begin
                act_reg  <= act_in;
                psum_reg <= psum_in + $signed(prod);
            end
        end
    end
endmodule

modules/Unit_test/pe/pe_tb.sv
`timescale 1ns/1ps

`define ACT_WIDTH 16
`define WT_WIDTH 16
`define PSUM_WIDTH 32

module pe_tb;

  reg clk;
  reg rst_n;
  reg en;
  reg load_weight;

  reg signed [`ACT_WIDTH-1:0]  act_in;
  reg signed [`WT_WIDTH-1:0]   weight_in;
  reg signed [`PSUM_WIDTH-1:0] psum_in;

  wire signed [`ACT_WIDTH-1:0]  act_out;
  wire signed [`PSUM_WIDTH-1:0] psum_out;

  // 20 time-unit clock period (same as mac_tb)
  always #10 clk = ~clk;

  pe #(
    .ACT_WIDTH(`ACT_WIDTH),
    .WT_WIDTH(`WT_WIDTH),
    .PSUM_WIDTH(`PSUM_WIDTH)
  ) dut (
    .clk(clk),
    .rst_n(rst_n),
    .en(en),
    .load_weight(load_weight),
    .act_in(act_in),
    .weight_in(weight_in),
    .psum_in(psum_in),
    .act_out(act_out),
    .psum_out(psum_out)
  );

  task automatic check(input string name, input integer got, input integer exp);
    begin
      $display("%s = %0d (exp %0d)", name, got, exp);
      if (got !== exp) begin
        $display("FAIL: %s mismatch", name);
        $fatal(1);
      end
    end
  endtask

  initial begin
    // init
    clk         = 0;
    rst_n       = 1;
    en          = 0;
    load_weight = 0;
    act_in      = 0;
    weight_in   = 0;
    psum_in     = 0;

    // reset pulse (active-low)
    #20 rst_n = 0;
    #20 rst_n = 1;

    // Load weight = -5 (only updates weight_reg)
    load_weight = 1;
    weight_in   = -5;
    #20;

    // MAC cycle 1: act=12, psum=-7 => -7 + 12*(-5) = -67
    load_weight = 0;
    en          = 1;
    act_in      = 12;
    psum_in     = -7;
    #20;
    check("act_out",  act_out,  12);
    check("psum_out", psum_out, -67);

    // MAC cycle 2: act=3, psum=16 => 16 + 3*(-5) = 1
    act_in  = 3;
    psum_in = 16;
    #20;
    check("act_out",  act_out,  3);
    check("psum_out", psum_out, 1);

    // Freeze outputs when en=0
    en      = 0;
    act_in  = 9;
    psum_in = 100;
    #20;
    check("act_out (frozen)",  act_out,  3);
    check("psum_out (frozen)", psum_out, 1);

    // load_weight priority over en (act/psum should not update on this cycle)
    en          = 1;
    load_weight = 1;
    weight_in   = 4;
    act_in      = 7;
    psum_in     = 10;
    #20;
    check("act_out (still frozen by load_weight)",  act_out,  3);
    check("psum_out (still frozen by load_weight)", psum_out, 1);

    // Now compute with new weight=4: 10 + 7*4 = 38
    load_weight = 0;
    act_in      = 7;
    psum_in     = 10;
    #20;
    check("act_out",  act_out,  7);
    check("psum_out", psum_out, 38);

    $display("Test finished!");
    $finish;
  end

  // Icarus/GTKWave VCD dump
  initial begin
    $dumpfile("dump.vcd");
    $dumpvars(0, pe_tb);
  end

endmodule

modules/Unit_test/pe/dump.vcd
$date
	Sat Feb 21 13:22:40 2026
$end
$version
	Icarus Verilog
$end
$timescale
	1ps
$end
$scope module pe_tb $end
$var wire 32 ! psum_out [31:0] $end
$var wire 16 " act_out [15:0] $end
$var reg 16 # act_in [15:0] $end
$var reg 1 $ clk $end
$var reg 1 % en $end
$var reg 1 & load_weight $end
$var reg 32 ' psum_in [31:0] $end
$var reg 1 ( rst_n $end
$var reg 16 ) weight_in [15:0] $end
$scope module dut $end
$var wire 16 * act_in [15:0] $end
$var wire 16 + act_out [15:0] $end
$var wire 1 $ clk $end
$var wire 1 % en $end
$var wire 1 & load_weight $end
$var wire 32 , psum_in [31:0] $end
$var wire 32 - psum_out [31:0] $end
$var wire 1 ( rst_n $end
$var wire 16 . weight_in [15:0] $end
$var wire 32 / prod [31:0] $end
$var parameter 32 0 ACT_WIDTH $end
$var parameter 32 1 PSUM_WIDTH $end
$var parameter 32 2 WT_WIDTH $end
$var reg 16 3 act_reg [15:0] $end
$var reg 32 4 psum_reg [31:0] $end
$var reg 16 5 weight_reg [15:0] $end
$upscope $end
$scope task check $end
$upscope $end
$upscope $end
$enddefinitions $end
$comment Show the parameter values. $end
$dumpall
b10000 2
b100000 1
b10000 0
$end
#0
$dumpvars
bx 5
bx 4
bx 3
bx /
b0 .
bx -
b0 ,
bx +
b0 *
b0 )
1(
b0 '
0&
0%
0$
b0 #
bx "
bx !
$end
#5000
1$
#10000
0$
#15000
1$
#20000
b0 !
b0 -
b0 4
b0 "
b0 +
b0 3
b0 /
b0 5
0$
0(
#25000
1$
#30000
0$
#35000
1$
#40000
0$
b1111111111111011 )
b1111111111111011 .
1&
1(
#45000
b1111111111111011 5
1$
#50000
0$
#55000
1$
#60000
0$
b11111111111111111111111111111001 '
b11111111111111111111111111111001 ,
b11111111111111111111111111000100 /
b1100 #
b1100 *
1%
0&
#65000
b11111111111111111111111110111101 !
b11111111111111111111111110111101 -
b11111111111111111111111110111101 4
b1100 "
b1100 +
b1100 3
1$
#70000
0$
#75000
1$
#80000
0$
b10000 '
b10000 ,
b11111111111111111111111111110001 /
b11 #
b11 *
#85000
b1 !
b1 -
b1 4
b11 "
b11 +
b11 3
1$
#90000
0$
#95000
1$
#100000
0$
b1100100 '
b1100100 ,
b11111111111111111111111111010011 /
b1001 #
b1001 *
0%
#105000
1$
#110000
0$
#115000
1$
#120000
0$
b1010 '
b1010 ,
b11111111111111111111111111011101 /
b111 #
b111 *
b100 )
b100 .
1&
1%
#125000
b11100 /
b100 5
1$
#130000
0$
#135000
1$
#140000
0$
0&
#145000
b100110 !
b100110 -
b100110 4
b111 "
b111 +
b111 3
1$
