modules/pe/pe.sv
// Final goal is to make a weight-stationary systolic array

module pe #(
// Subject to change
    parameter ACT_WIDTH = 16,
    parameter WT_WIDTH = 16,
    parameter PSUM_WIDTH = 32                       // to prevent overflow.
)(
    input  logic clk,
    input  logic rst_n,
    input  logic en,                                // 1: activates the PE,     0: freezes it
    input  logic load_weight,                       // 1: loads in new weight,  0: latches current weight, compute MAC. 

    // Data Inputs
    input  logic signed [ACT_WIDTH-1:0]  act_in,    // From left PE (or Skew FIFO)
    input  logic signed [WT_WIDTH-1:0]   weight_in, // From top PE (or Weight FIFO)
    input  logic signed [PSUM_WIDTH-1:0] psum_in,   // From top PE (or set to 0 at top row)

    // Data Outputs
    output logic signed [ACT_WIDTH-1:0]  act_out,   // To right PE
    output logic signed [PSUM_WIDTH-1:0] psum_out   // To bottom PE (or ReLU block)
);

    // Internal registers
    logic signed [WT_WIDTH-1:0] weight_reg;
    logic signed [ACT_WIDTH-1:0]  act_reg;
    logic signed [PSUM_WIDTH-1:0] psum_reg;

    assign act_out = act_reg;
    assign psum_out = psum_reg;

    logic signed [ACT_WIDTH+WT_WIDTH-1:0] prod;
    assign prod = act_in * weight_reg;

    always_ff @(posedge clk or negedge rst_n) begin
        if (!rst_n) begin
            weight_reg <= '0;
            act_reg    <= '0;
            psum_reg   <= '0;
        end else begin
            if (load_weight) begin
                weight_reg <= weight_in;
            end
            else if (en) begin
                act_reg  <= act_in;
                psum_reg <= psum_in + $signed(prod);
            end
        end
    end
endmodule

modules/Unit_test/pe/pe_tb.sv
`timescale 1ns/1ps

`define ACT_WIDTH 16
`define WT_WIDTH 16
`define PSUM_WIDTH 32

module pe_tb;

  reg clk;
  reg rst_n;
  reg en;
  reg load_weight;

  reg signed [`ACT_WIDTH-1:0]  act_in;
  reg signed [`WT_WIDTH-1:0]   weight_in;
  reg signed [`PSUM_WIDTH-1:0] psum_in;

  wire signed [`ACT_WIDTH-1:0]  act_out;
  wire signed [`PSUM_WIDTH-1:0] psum_out;

  // 20 time-unit clock period (same as mac_tb)
  always #10 clk = ~clk;

  pe #(
    .ACT_WIDTH(`ACT_WIDTH),
    .WT_WIDTH(`WT_WIDTH),
    .PSUM_WIDTH(`PSUM_WIDTH)
  ) dut (
    .clk(clk),
    .rst_n(rst_n),
    .en(en),
    .load_weight(load_weight),
    .act_in(act_in),
    .weight_in(weight_in),
    .psum_in(psum_in),
    .act_out(act_out),
    .psum_out(psum_out)
  );

  task automatic check(input string name, input integer got, input integer exp);
    begin
      $display("%s = %0d (exp %0d)", name, got, exp);
      if (got !== exp) begin
        $display("FAIL: %s mismatch", name);
        $fatal(1);
      end
    end
  endtask

  initial begin
    // init
    clk         = 0;
    rst_n       = 1;
    en          = 0;
    load_weight = 0;
    act_in      = 0;
    weight_in   = 0;
    psum_in     = 0;

    // reset pulse (active-low)
    #20 rst_n = 0;
    #20 rst_n = 1;

    // Load weight = -5 (only updates weight_reg)
    load_weight = 1;
    weight_in   = -5;
    #20;

    // MAC cycle 1: act=12, psum=-7 => -7 + 12*(-5) = -67
    load_weight = 0;
    en          = 1;
    act_in      = 12;
    psum_in     = -7;
    #20;
    check("act_out",  act_out,  12);
    check("psum_out", psum_out, -67);

    // MAC cycle 2: act=3, psum=16 => 16 + 3*(-5) = 1
    act_in  = 3;
    psum_in = 16;
    #20;
    check("act_out",  act_out,  3);
    check("psum_out", psum_out, 1);

    // Freeze outputs when en=0
    en      = 0;
    act_in  = 9;
    psum_in = 100;
    #20;
    check("act_out (frozen)",  act_out,  3);
    check("psum_out (frozen)", psum_out, 1);

    // load_weight priority over en (act/psum should not update on this cycle)
    en          = 1;
    load_weight = 1;
    weight_in   = 4;
    act_in      = 7;
    psum_in     = 10;
    #20;
    check("act_out (still frozen by load_weight)",  act_out,  3);
    check("psum_out (still frozen by load_weight)", psum_out, 1);

    // Now compute with new weight=4: 10 + 7*4 = 38
    load_weight = 0;
    act_in      = 7;
    psum_in     = 10;
    #20;
    check("act_out",  act_out,  7);
    check("psum_out", psum_out, 38);

    $display("Test finished!");
    $finish;
  end

  // Icarus/GTKWave VCD dump
  initial begin
    $dumpfile("dump.vcd");
    $dumpvars(0, pe_tb);
  end

endmodule

Vivado_sim/Vivado_sim.sim/sim_1/behav/xsim/dump.vcd
$date
   Fri Mar  6 14:22:06 2026
$end

$version
  2025.1.0
  $dumpfile ("dump.vcd") 
$end

$timescale
  1ps
$end

$scope module pe_tb $end
$var reg 1 ! clk $end
$var reg 1 " rst_n $end
$var reg 1 # en $end
$var reg 1 $ load_weight $end
$var reg 16 % act_in [15:0] $end
$var reg 16 & weight_in [15:0] $end
$var reg 32 ' psum_in [31:0] $end
$var wire 16 ( act_out [15:0] $end
$var wire 32 ) psum_out [31:0] $end
$scope module dut $end
$var wire 1 * clk $end
$var wire 1 + rst_n $end
$var wire 1 , en $end
$var wire 1 - load_weight $end
$var wire 16 . act_in [15:0] $end
$var wire 16 / weight_in [15:0] $end
$var wire 32 0 psum_in [31:0] $end
$var reg 16 1 act_out [15:0] $end
$var reg 32 2 psum_out [31:0] $end
$var reg 16 3 weight_reg [15:0] $end
$var reg 16 4 act_reg [15:0] $end
$var reg 32 5 psum_reg [31:0] $end
$var reg 32 6 prod [31:0] $end
$upscope $end
$scope task check $end
$upscope $end
$upscope $end
$enddefinitions $end

#0
$dumpvars
0!
1"
0#
0$
b0 %
b0 &
b0 '
bx (
bx )
0*
1+
0,
0-
b0 .
b0 /
b0 0
bx 1
bx 2
bx 3
bx 4
bx 5
bx 6
$end

#10000
1!
1*

#20000
0!
0"
b0 (
b0 )
0*
0+
b0 1
b0 2
b0 3
b0 4
b0 5
b0 6

#30000
1!
1*

#40000
0!
1"
1$
b1111111111111011 &
0*
1+
1-
b1111111111111011 /

#50000
1!
1*
b1111111111111011 3

#60000
0!
1#
0$
b1100 %
b11111111111111111111111111111001 '
0*
1,
0-
b1100 .
b11111111111111111111111111111001 0
b11111111111111111111111111000100 6

#70000
1!
b1100 (
b11111111111111111111111110111101 )
1*
b1100 1
b11111111111111111111111110111101 2
b1100 4
b11111111111111111111111110111101 5

#80000
0!
b11 %
b10000 '
0*
b11 .
b10000 0
b11111111111111111111111111110001 6

#90000
1!
b11 (
b1 )
1*
b11 1
b1 2
b11 4
b1 5

#100000
0!
0#
b1001 %
b1100100 '
0*
0,
b1001 .
b1100100 0
b11111111111111111111111111010011 6

#110000
1!
1*

#120000
0!
1#
1$
b111 %
b100 &
b1010 '
0*
1,
1-
b111 .
b100 /
b1010 0
b11111111111111111111111111011101 6

#130000
1!
1*
b100 3
b11100 6

#140000
0!
0$
0*
0-

#150000
1!
b111 (
b100110 )
1*
b111 1
b100110 2
b111 4
b100110 5
